prettyetc_qt/__init__.py
prettyetc_qt/containers.py
prettyetc_qt/inputs.py
prettyetc_qt/main.py
prettyetc_qt/settings.py
prettyetc_qt/utils.py
prettyetc_qt/components/__init__.py
prettyetc_qt/components/widgets/__init__.py
prettyetc_qt/components/widgets/about.py
prettyetc_qt/components/widgets/add.py
prettyetc_qt/components/widgets/details.py
prettyetc_qt/components/widgets/find.py
prettyetc_qt/components/widgets/input.py
prettyetc_qt/components/widgets/logo_rc.py
prettyetc_qt/components/widgets/mainwindow.py
prettyetc_qt/components/widgets/qt_conf_rc.py
prettyetc_qt/components/widgets/settings.py
prettyetc_qt/components/widgets/treeview.py
prettyetc_qt/fieldviews/__init__.py
prettyetc_qt/fieldviews/common.py
prettyetc_qt/fieldviews/context.py
prettyetc_qt/fieldviews/details.py
prettyetc_qt/fieldviews/treeview.py
prettyetc_qt/themes/DefinitiveDark.qss
prettyetc_qt/themes/QTDark.qss
prettyetc_qt/themes/__init__.py
prettyetc_qt/themes/darkorange.qss
prettyetc_qt/themes/GTRONICK-QSS/AMOLED.qss
prettyetc_qt/themes/GTRONICK-QSS/Aqua.qss
prettyetc_qt/themes/GTRONICK-QSS/ConsoleStyle.qss
prettyetc_qt/themes/GTRONICK-QSS/ElegantDark.qss
prettyetc_qt/themes/GTRONICK-QSS/LICENSE
prettyetc_qt/themes/GTRONICK-QSS/MaterialDark.qss
prettyetc_qt/themes/GTRONICK-QSS/README.md
prettyetc_qt/themes/GTRONICK-QSS/Ubuntu.qss
prettyetc_qt-0.4.0.dist-info/LICENSE
prettyetc_qt-0.4.0.dist-info/METADATA
prettyetc_qt-0.4.0.dist-info/WHEEL
prettyetc_qt-0.4.0.dist-info/entry_points.txt
prettyetc_qt-0.4.0.dist-info/top_level.txt
prettyetc_qt-0.4.0.dist-info/RECORD
