Metadata-Version: 2.1
Name: prettyetc-qt
Version: 0.4.0
Summary: See your configuration files using a pretty and universal interface.
Home-page: https://gitlab.com/prettyetc/prettyetc
Author: trollodel
License: UNKNOWN
Project-URL: Bug Reports, https://gitlab.com/prettyetc/prettyetc/issues
Project-URL: Documentation, https://prettyetc.gitlab.io/prettyetc/
Project-URL: Source, https://gitlab.com/prettyetc/prettyetc
Keywords: config json ini etc xml qt
Platform: UNKNOWN
Classifier: Development Status :: 5 - Production/Stable
Classifier: License :: OSI Approved :: GNU General Public License v3 (GPLv3)
Classifier: Programming Language :: Python :: 3 :: Only
Classifier: Programming Language :: Python :: 3
Classifier: Programming Language :: Python :: 3.5
Classifier: Programming Language :: Python :: 3.6
Classifier: Programming Language :: Python :: 3.7
Classifier: Programming Language :: Python :: 3.8
Classifier: Operating System :: OS Independent
Classifier: Topic :: Documentation :: Sphinx
Classifier: Topic :: System :: Systems Administration
Classifier: Topic :: Text Processing
Classifier: Topic :: Utilities
Classifier: Intended Audience :: Developers
Classifier: Intended Audience :: System Administrators
Requires-Python: >=3.5, <4
Requires-Dist: PySide2
Requires-Dist: prettyetc[all] (>=0.4.0rc2)
